LICENSE
MANIFEST.in
README.md
setup.py
SRJSON2Mantle/__init__.py
SRJSON2Mantle/cli.py
SRJSON2Mantle/objc_template.py
SRJSON2Mantle/renderer.py
SRJSON2Mantle/utils.py
SRJSON2Mantle.egg-info/PKG-INFO
SRJSON2Mantle.egg-info/SOURCES.txt
SRJSON2Mantle.egg-info/dependency_links.txt
SRJSON2Mantle.egg-info/entry_points.txt
SRJSON2Mantle.egg-info/not-zip-safe
SRJSON2Mantle.egg-info/top_level.txt
SRJSON2Mantle/templates/model.h
SRJSON2Mantle/templates/model.m