Metadata-Version: 1.1
Name: SRJSON2Mantle
Version: 1.1.3
Summary: Generate Mantle models using JSON files
Home-page: https://github.com/seandeng/SRJSON2Mantle
Author: seandeng
Author-email: dsr_22@foxmail.com
License: MIT
Keywords: mantle parser objective-c
Platform: UNKNOWN
Classifier: Development Status :: 4 - Beta
Classifier: License :: OSI Approved :: MIT License
Classifier: Intended Audience :: Developers
Classifier: Programming Language :: Python :: 2.7
Classifier: Programming Language :: Python :: 3.4
Classifier: Programming Language :: Objective C
Classifier: Topic :: Text Processing
